LICENSE
README.md
setup.py
argcfg/__init__.py
argcfg/config.py
argcfg/parser_utils.py
argcfg.egg-info/PKG-INFO
argcfg.egg-info/SOURCES.txt
argcfg.egg-info/dependency_links.txt
argcfg.egg-info/top_level.txt